procode/__init__.py
procode/definitions.py
procode/procode.py
procode/cli/__init__.py
procode/cli/config.py
procode/cli/inventory.py
procode/cli/main.py
procode/cli/publish.py
procode/cli/script.py
procode/cli/setup.py
procode/cli/surreal.py
procode/cli/sync.py
procode/cli/task.py
procode/cli/wingdbstub.py
procode/cli/workspace.py
procode/helpers/__init__.py
procode/helpers/faker.py
procode/helpers/general.py
procode/helpers/loaders.py
procode/helpers/models.py
procode/helpers/surreal.py
procode/logic/__init__.py
procode/logic/crawler.py
procode/logic/inventory.py
procode/logic/procode.py
procode/mappers/__init__.py
procode/mappers/inventory.py
procode/models/__init__.py
procode/models/base.py
procode/models/config.py
procode/models/enums.py
procode/models/inventory.py
procode/models/procode.py
procode/models/script.py
procode/models/task.py
procode/ports/__init__.py
procode/ports/preferences.py
procode/storage/__init__.py
procode/storage/surreal.py
procode-0.1.0.dist-info/licenses/AUTHORS.rst
procode-0.1.0.dist-info/licenses/LICENSE
procode-0.1.0.dist-info/METADATA
procode-0.1.0.dist-info/WHEEL
procode-0.1.0.dist-info/entry_points.txt
procode-0.1.0.dist-info/top_level.txt
procode-0.1.0.dist-info/RECORD
