Metadata-Version: 2.4
Name: procode
Version: 0.1.0
Summary: ProcCode Builder Assistant
Home-page: https://github.com/asteriogonzalez/procode
Author: Asterio Gonzalez
Author-email: asterio.gonzalez@gmail.com
Keywords: procode
Classifier: Development Status :: 2 - Pre-Alpha
Classifier: Intended Audience :: Developers
Classifier: Natural Language :: English
Classifier: Programming Language :: Python :: 3.10
Classifier: Programming Language :: Python :: 3.11
Requires-Python: >=3.10
License-File: LICENSE
License-File: AUTHORS.rst
Requires-Dist: agptools>=0.1.85
Requires-Dist: syncmodels>=0.1.85
Requires-Dist: pydantic
Requires-Dist: datamodel-code-generator
Requires-Dist: datamodel-code-generator[http]
Requires-Dist: datamodel-code-generator[graphql]
Requires-Dist: aiohttp
Requires-Dist: aiocache
Requires-Dist: Click
Requires-Dist: glom
Requires-Dist: jmespath
Requires-Dist: fastapi
Requires-Dist: geopy
Requires-Dist: requests
Requires-Dist: rich
Requires-Dist: surrealist
Requires-Dist: uvicorn
Requires-Dist: uvloop
Requires-Dist: watchfiles
Requires-Dist: websockets>=11.0
Requires-Dist: faker
Requires-Dist: setuptools
Dynamic: author
Dynamic: author-email
Dynamic: classifier
Dynamic: description
Dynamic: home-page
Dynamic: keywords
Dynamic: license-file
Dynamic: requires-dist
Dynamic: requires-python
Dynamic: summary
